{
    "entry_1": {
        "AT": 134.7,
        "BE": 166.9,
        "BG": 147.8,
        "CY": 146.8,
        "CZ": 142.7,
        "DE": 145.9,
        "DK": 183.5,
        "EE": 169.2,
        "EL": 131.8,
        "ES": 149.5,
        "FI": 133.7,
        "FR": 140.1,
        "HR": 146.4,
        "HU": 231.1,
        "IE": 123.8,
        "IT": 145,
        "LT": 152.3,
        "LU": 141,
        "LV": 171.6,
        "MT": 117.5,
        "NL": 144.3,
        "PL": 160.3,
        "PT": 128.4,
        "RO": 208.4,
        "SI": 148.3,
        "SK": 177.9
    },
    "entry_2": {
        "AT": 136.1,
        "BE": 169.9,
        "BG": 157.2,
        "CY": 151.6,
        "CZ": 142.8,
        "DE": 145.6,
        "DK": 182.6,
        "EE": 168.7,
        "EL": 135,
        "ES": 149.9,
        "FI": 134.2,
        "FR": 140.2,
        "HR": 147.3,
        "HU": 225.8,
        "IE": 130.9,
        "IT": 139.3,
        "LT": 153.6,
        "LU": 143.2,
        "LV": 176.7,
        "MT": 118.7,
        "NL": 153.6,
        "PL": 159.9,
        "PT": 128.7,
        "RO": 209.4,
        "SI": 148.5,
        "SK": 185.6
    },
    "entry_3": {
        "AT": 148.4,
        "BE": 213.3,
        "BG": 214.4,
        "CY": 156.7,
        "CZ": 136.9,
        "DE": 152.3,
        "DK": 201.4,
        "EE": 192.9,
        "EL": 146.3,
        "ES": 147.2,
        "FI": 151.2,
        "FR": 153.4,
        "HR": 145.6,
        "HU": 306.4,
        "IE": 213.3,
        "IT": 207,
        "LT": 160.1,
        "LU": 141.6,
        "LV": 245.9,
        "MT": 119.2,
        "NL": 163.6,
        "PL": 171.8,
        "PT": 132.8,
        "RO": 258.2,
        "SI": 145.9,
        "SK": 148.3
    },
    "entry_4": {
        "AT": 139.2,
        "BE": 163.5,
        "BG": 159.9,
        "CY": 145.6,
        "CZ": 143.6,
        "DE": 147.3,
        "DK": 186.2,
        "EE": 169.6,
        "EL": 136.5,
        "ES": 149.7,
        "FI": 134.1,
        "FR": 143.2,
        "HR": 145.6,
        "HU": 241.2,
        "IE": 148.6,
        "IT": 153.2,
        "LT": 154.8,
        "LU": 143,
        "LV": 177.7,
        "MT": 117.2,
        "NL": 154.3,
        "PL": 162.5,
        "PT": 129.1,
        "RO": 215.7,
        "SI": 148.6,
        "SK": 188.5
    },
    "entry_5": {
        "AT": 142.9,
        "BE": 173.8,
        "BG": 164.8,
        "CY": 145.4,
        "CZ": 143.5,
        "DE": 150.7,
        "DK": 187.9,
        "EE": 170.3,
        "EL": 134.5,
        "ES": 152.1,
        "FI": 138.9,
        "FR": 146,
        "HR": 144.3,
        "HU": 246.6,
        "IE": 140.4,
        "IT": 154.6,
        "LT": 156.4,
        "LU": 143.8,
        "LV": 182.8,
        "MT": 116.8,
        "NL": 161,
        "PL": 164.7,
        "PT": 130,
        "RO": 222.7,
        "SI": 147.6,
        "SK": 188.8
    }
}

