{
    "entry_1": {
        "AT": 139,
        "BE": 177.3,
        "BG": 154.7,
        "CY": 147.7,
        "CZ": 142.8,
        "DE": 147.3,
        "DK": 185.2,
        "EE": 170,
        "EL": 134.4,
        "ES": 145.7,
        "FI": 131.9,
        "FR": 146.9,
        "HR": 139.5,
        "HU": 244.8,
        "IE": 127.7,
        "IT": 150.3,
        "LT": 150.2,
        "LU": 139.2,
        "LV": 173.1,
        "MT": 117.3,
        "NL": 146.1,
        "PL": 162.3,
        "PT": 127.3,
        "RO": 219.6,
        "SI": 149.4,
        "SK": 180.9
    },
    "entry_2": {
        "AT": 142,
        "BE": 170.5,
        "BG": 163.4,
        "CY": 146,
        "CZ": 142.9,
        "DE": 147.1,
        "DK": 186.6,
        "EE": 170.6,
        "EL": 133.2,
        "ES": 146.5,
        "FI": 133.8,
        "FR": 142.2,
        "HR": 142.5,
        "HU": 242,
        "IE": 137.9,
        "IT": 144.6,
        "LT": 150.9,
        "LU": 144.5,
        "LV": 178.8,
        "MT": 118,
        "NL": 155,
        "PL": 163.1,
        "PT": 128.1,
        "RO": 221.2,
        "SI": 148.4,
        "SK": 190.5
    },
    "entry_3": {
        "AT": 148,
        "BE": 212.4,
        "BG": 210.1,
        "CY": 152.5,
        "CZ": 137.4,
        "DE": 153,
        "DK": 200.6,
        "EE": 190.5,
        "EL": 146.4,
        "ES": 148.5,
        "FI": 150.7,
        "FR": 152.2,
        "HR": 145.3,
        "HU": 291.9,
        "IE": 210.1,
        "IT": 200,
        "LT": 161.2,
        "LU": 141.6,
        "LV": 236.6,
        "MT": 118.7,
        "NL": 163.8,
        "PL": 170.5,
        "PT": 133,
        "RO": 250.9,
        "SI": 145.4,
        "SK": 150.5
    },
    "entry_4": {
        "AT": 149.2,
        "BE": 178.1,
        "BG": 165.4,
        "CY": 144.9,
        "CZ": 144.9,
        "DE": 150.6,
        "DK": 187.5,
        "EE": 170.5,
        "EL": 137.3,
        "ES": 146.6,
        "FI": 133.9,
        "FR": 151.4,
        "HR": 143.8,
        "HU": 250.3,
        "IE": 142.3,
        "IT": 153.5,
        "LT": 151,
        "LU": 146.1,
        "LV": 182,
        "MT": 116.6,
        "NL": 158.2,
        "PL": 165.7,
        "PT": 126.9,
        "RO": 223.9,
        "SI": 148.6,
        "SK": 196
    },
    "entry_5": {
        "AT": 147.2,
        "BE": 194.7,
        "BG": 173,
        "CY": 145.9,
        "CZ": 145.8,
        "DE": 151.8,
        "DK": 189.8,
        "EE": 172.4,
        "EL": 139.5,
        "ES": 153.3,
        "FI": 141,
        "FR": 148.8,
        "HR": 144.6,
        "HU": 248.6,
        "IE": 155.3,
        "IT": 158.6,
        "LT": 162.2,
        "LU": 144.8,
        "LV": 189.7,
        "MT": 116.6,
        "NL": 165.7,
        "PL": 166,
        "PT": 132,
        "RO": 226.1,
        "SI": 147.1,
        "SK": 193.6
    }
}

