{
    "entry_1": {
        "AT": 147.8,
        "BE": 217.2,
        "BG": 203.1,
        "CY": 143.2,
        "CZ": 143,
        "DE": 155.8,
        "DK": 193,
        "EE": 188.9,
        "EL": 147.2,
        "ES": 155,
        "FI": 147.9,
        "FR": 151,
        "HR": 144.8,
        "HU": 250.1,
        "IE": 212.1,
        "IT": 178.2,
        "LT": 168.6,
        "LU": 143.6,
        "LV": 210.3,
        "MT": 117.7,
        "NL": 164.4,
        "PL": 168.7,
        "PT": 130.5,
        "RO": 246.6,
        "SI": 143.5,
        "SK": 163.8
    },
    "entry_2": {
        "AT": 147,
        "BE": 214.9,
        "BG": 199.6,
        "CY": 143.3,
        "CZ": 139.5,
        "DE": 157.6,
        "DK": 191.4,
        "EE": 186,
        "EL": 149.2,
        "ES": 154.5,
        "FI": 150.5,
        "FR": 147.5,
        "HR": 145.6,
        "HU": 259.1,
        "IE": 224.1,
        "IT": 178.7,
        "LT": 169.4,
        "LU": 143.5,
        "LV": 209,
        "MT": 116.5,
        "NL": 165.2,
        "PL": 166.2,
        "PT": 132.6,
        "RO": 236.4,
        "SI": 142.7,
        "SK": 168.7
    },
    "entry_3": {
        "AT": 147.2,
        "BE": 210,
        "BG": 201.4,
        "CY": 145.1,
        "CZ": 139.1,
        "DE": 155.7,
        "DK": 198.4,
        "EE": 185.7,
        "EL": 147.1,
        "ES": 152.7,
        "FI": 149.4,
        "FR": 149.4,
        "HR": 144.6,
        "HU": 262.9,
        "IE": 203.6,
        "IT": 186.1,
        "LT": 164.2,
        "LU": 142.5,
        "LV": 214.5,
        "MT": 117.5,
        "NL": 164.5,
        "PL": 167.3,
        "PT": 132.5,
        "RO": 236.4,
        "SI": 144.1,
        "SK": 157
    },
    "entry_4": {
        "AT": 144.3,
        "BE": 209.9,
        "BG": 198.7,
        "CY": 143.7,
        "CZ": 141.3,
        "DE": 160.1,
        "DK": 192.6,
        "EE": 181.2,
        "EL": 151.3,
        "ES": 156.3,
        "FI": 147.6,
        "FR": 146,
        "HR": 145,
        "HU": 247.3,
        "IE": 193.6,
        "IT": 175.3,
        "LT": 166.7,
        "LU": 139.9,
        "LV": 203.5,
        "MT": 116.7,
        "NL": 165.1,
        "PL": 164.3,
        "PT": 132.3,
        "RO": 226.3,
        "SI": 143.5,
        "SK": 169.4
    }
}

