{
  "entry_1": {"AT":123.6,"BE":126.2,"BG":128.7,"CY":133.8,"CZ":115.1,"DE":95.4,"DK":129.3,"EE":118,"EL":124,"ES":106.5,"FI":117.2,"FR":97.3,"HR":111.8,"HU":126.9,"IT":104.4,"LT":153.6,"LV":122.4,"MT":111.2,"PL":152.4,"PT":98.5,"RO":108.3,"SE":124,"SI":128.4,"SK":107.9},
  "entry_2": {"AT":126.4,"BE":125.8,"BG":128.2,"CY":133.3,"CZ":114.7,"DE":95.5,"DK":131.5,"EE":125.2,"EL":121.7,"ES":106.9,"FI":118.7,"FR":97.9,"HR":112.8,"HU":125.8,"IT":104.8,"LT":148.5,"LV":124.3,"MT":106.5,"PL":151.8,"PT":99.2,"RO":109,"SE":118.7,"SI":129.5,"SK":107.7},
  "entry_3": {"AT":123.8,"BE":126.4,"BG":129.1,"CY":133.3,"CZ":115.5,"DE":95.4,"DK":130.5,"EE":120.6,"EL":121.6,"ES":106.3,"FI":118.3,"FR":97.4,"HR":112.8,"HU":127.5,"IT":104.4,"LT":152.1,"LV":123.5,"MT":108,"PL":152.8,"PT":98.5,"RO":108.7,"SE":122.7,"SI":129.1,"SK":108.4},
  "entry_4": {
    "AT": null,
    "BE": null,
    "BG": null,
    "CY": null,
    "CZ": null,
    "DE": null,
    "DK": null,
    "EE": null,
    "EL": null,
    "ES": null,
    "FI": null,
    "FR": null,
    "HR": null,
    "HU": null,
    "IT": null,
    "LT": null,
    "LV": null,
    "MT": null,
    "PL": null,
    "PT": null,
    "RO": null,
    "SE": null,
    "SI": null,
    "SK": null
  },
  "entry_5": {
    "AT": null,
    "BE": null,
    "BG": null,
    "CY": null,
    "CZ": null,
    "DE": null,
    "DK": null,
    "EE": null,
    "EL": null,
    "ES": null,
    "FI": null,
    "FR": null,
    "HR": null,
    "HU": null,
    "IT": null,
    "LT": null,
    "LV": null,
    "MT": null,
    "PL": null,
    "PT": null,
    "RO": null,
    "SE": null,
    "SI": null,
    "SK": null
  }
}
